libgeohash/__init__.py
libgeohash/distance_metrics.py
libgeohash/geohash_base.py
libgeohash/geometry.py
libgeohash-0.1.1.dist-info/LICENSE
libgeohash-0.1.1.dist-info/METADATA
libgeohash-0.1.1.dist-info/WHEEL
libgeohash-0.1.1.dist-info/top_level.txt
libgeohash-0.1.1.dist-info/RECORD
