Metadata-Version: 2.1
Name: libgeohash
Version: 0.1.1
Summary: Python library for interacting with geohashes.
Home-page: https://github.com/bashhike/libgeohash
Author: Abhishek Pandey
Author-email: ashp.pandey916@gmail.com
License: MIT
Download-URL: https://github.com/bashhike/libgeohash/archive/0.1.tar.gz
Keywords: geohash,polygon to geohash,shapely,geohashes
Platform: UNKNOWN
Classifier: Development Status :: 3 - Alpha
Classifier: Intended Audience :: Developers
Classifier: Topic :: Software Development :: Libraries :: Python Modules
Classifier: License :: OSI Approved :: MIT License
Classifier: Programming Language :: Python :: 3
Classifier: Programming Language :: Python :: 3.4
Classifier: Programming Language :: Python :: 3.5
Classifier: Programming Language :: Python :: 3.6
Requires-Dist: shapely
